ptctools/__init__.py
ptctools/_portainer.py
ptctools/_s3.py
ptctools/cli.py
ptctools/config.py
ptctools/db.py
ptctools/stack.py
ptctools/utils.py
ptctools/volume.py
ptctools-0.1.0.dist-info/METADATA
ptctools-0.1.0.dist-info/WHEEL
ptctools-0.1.0.dist-info/entry_points.txt
ptctools-0.1.0.dist-info/licenses/LICENSE
ptctools-0.1.0.dist-info/RECORD
