Metadata-Version: 2.4
Name: ptctools
Version: 0.1.0
Summary: Portainer Client Tools - CLI for managing Portainer from client
License-File: LICENSE
Requires-Python: >=3.10
Requires-Dist: click>=8.0
Provides-Extra: dev
Requires-Dist: pytest>=8.0; extra == 'dev'
